{
  "project_info": {
    "project_number": "1062875572182",
    "project_id": "nativeriderchat-353df",
    "storage_bucket": "nativeriderchat-353df.firebasestorage.app"
  },
  "client": [
    {
      "client_info": {
        "mobilesdk_app_id": "1:1062875572182:android:b43d56a8feaefa61322677",
        "android_client_info": {
          "package_name": "com.nativerider"
        }
      },
      "oauth_client": [],
      "api_key": [
        {
          "current_key": "AIzaSyDC0UBAtj8HLET8Iw9ka_Goc3Wd7LCcgo8"
        }
      ],
      "services": {
        "appinvite_service": {
          "other_platform_oauth_client": []
        }
      }
    }
  ],
  "configuration_version": "1"
}